google_books_driver/__init__.py
google_books_driver/retrieve.py
google_books_driver-0.0.1.dist-info/LICENSE
google_books_driver-0.0.1.dist-info/METADATA
google_books_driver-0.0.1.dist-info/WHEEL
google_books_driver-0.0.1.dist-info/top_level.txt
google_books_driver-0.0.1.dist-info/RECORD
