Metadata-Version: 2.1
Name: google-books-driver
Version: 0.0.1
Summary: Functions required by the hirmeos-google-books-driver
Author-email: Cristian Garcia <cristian.garcia@ubiquitypress.com>
Classifier: Programming Language :: Python :: 3
Classifier: License :: OSI Approved :: MIT License
Classifier: Operating System :: OS Independent
Requires-Python: >=3.10
License-File: LICENSE
Requires-Dist: selenium >=4.0
Requires-Dist: webdriver-manager >=4.0
